fintekkers/__init__.py
fintekkers/devops/__init__.py
fintekkers/devops/aws_account_setup.py
fintekkers/devops/build_createEC2.py
fintekkers/devops/docker_image.py
fintekkers/devops/service.py
fintekkers/dummyGRPCService/__init__.py
fintekkers/dummyGRPCService/__main__.py
fintekkers/dummyGRPCService/app.py
fintekkers/dummyGRPCService/grpc.py
fintekkers/dummyGRPCService/generated/__init__.py
fintekkers/dummyGRPCService/generated/echo_pb2.py
fintekkers/dummyGRPCService/generated/echo_pb2_grpc.py
fintekkers/dummyService/__init__.py
fintekkers/dummyService/app.py
fintekkers_devops_scripts-0.0.7.dist-info/METADATA
fintekkers_devops_scripts-0.0.7.dist-info/WHEEL
fintekkers_devops_scripts-0.0.7.dist-info/top_level.txt
fintekkers_devops_scripts-0.0.7.dist-info/RECORD
