Metadata-Version: 2.1
Name: fintekkers-devops-scripts
Version: 0.0.7
Summary: Fintekkers DevOps package
Home-page: https://github.com/fintekkers/fintekkers-devops-scripts
Author: David Doherty
Author-email: dave@fintekkers.org
License: MIT
Keywords: fintekkers ledger models
Platform: UNKNOWN
Classifier: Programming Language :: Python :: 3
Classifier: Operating System :: MacOS :: MacOS X
